.bumpversion.cfg
CONTRIBUTING.md
LICENSE
MANIFEST.in
Makefile
README.md
pyproject.toml
setup.py
docs/Makefile
docs/make.bat
docs/source/conf.py
docs/source/examples.md
docs/source/index.rst
docs/source/installation.md
docs/source/modules.rst
docs/source/multi_scale_expansion.rst
multi_scale_expansion/__init__.py
multi_scale_expansion/__main__.py
multi_scale_expansion/classification.py
multi_scale_expansion/dataset.py
multi_scale_expansion/model.py
multi_scale_expansion.egg-info/PKG-INFO
multi_scale_expansion.egg-info/SOURCES.txt
multi_scale_expansion.egg-info/dependency_links.txt
multi_scale_expansion.egg-info/requires.txt
multi_scale_expansion.egg-info/top_level.txt
multi_scale_expansion/tests/test_all.py