Metadata-Version: 2.1
Name: multi-scale-expansion
Version: 0.1.2
Summary: Check whether your plants are healthy using image classification
Author-email: Angel Mancera <aem2283@columbia.edu>
License: MIT License
Project-URL: repository, https://github.com/ColumbiaMancera/multi-scale-expansion
Classifier: Programming Language :: Python :: 3.10
Requires-Python: >=3.7
Provides-Extra: develop
License-File: LICENSE
